README.md
setup.cfg
setup.py
targomo_python/__init__.py
targomo_python.egg-info/PKG-INFO
targomo_python.egg-info/SOURCES.txt
targomo_python.egg-info/dependency_links.txt
targomo_python.egg-info/requires.txt
targomo_python.egg-info/top_level.txt
targomo_python/cli/__init__.py
targomo_python/cli/__main__.py
targomo_python/rest/ServiceExecutor.py
targomo_python/rest/__init__.py
targomo_python/util/Configuration.py
targomo_python/util/TravelOptions.py
targomo_python/util/Util.py
targomo_python/util/__init__.py
targomo_python/util/enum/EdgeWeightType.py
targomo_python/util/enum/PathSerializerType.py
targomo_python/util/enum/PolygonIntersectionMode.py
targomo_python/util/enum/PolygonSerializationType.py
targomo_python/util/enum/TravelType.py
targomo_python/util/enum/__init__.py