Metadata-Version: 2.1
Name: targomo-python
Version: 0.23
Summary: A python client library to query the Targomo API
Home-page: https://github.com/targomo/targomo-python
Author: Targomo GmbH
Author-email: mail@targomo.com
License: UNKNOWN
Download-URL: https://github.com/targomo/targomo-python/tarball/0.23
Keywords: isochrone,routing,polygon,openstreetmaps,gtfs,map
Platform: UNKNOWN
